LICENSE
MANIFEST.in
README.md
setup.py
ai_notes_summaries.egg-info/PKG-INFO
ai_notes_summaries.egg-info/SOURCES.txt
ai_notes_summaries.egg-info/dependency_links.txt
ai_notes_summaries.egg-info/requires.txt
ai_notes_summaries.egg-info/top_level.txt
extractor/__init__.py
extractor/extract.py
extractor/models.py
extractor/poc.py
extractor/prompt.py
extractor/utils.py
extractor/examples/all-categories-multiple.txt
extractor/examples/no-action-items.txt
extractor/examples/no-key-themes.txt
extractor/examples/no-lessons.txt
summarizer/__init__.py
summarizer/poc.py
summarizer/summarize.py
summarizer/prompting/__init__.py
summarizer/prompting/prompt.py
summarizer/prompting/summarizer.txt