Metadata-Version: 2.1
Name: ai-notes-summaries
Version: 0.1.8
Summary: An AI-powered tool that extracts structured notes from a given piece of text.
Home-page: https://github.com/CodeWithOz/ai-notes-summaries
Author: Uche Ozoemena
Author-email: codewithoz@outlook.com
License: UNKNOWN
Platform: UNKNOWN
License-File: LICENSE
